nspd_package_q/__init__.py
nspd_package_q/nspd_q.py
nspd_quarters-0.1.2.dist-info/METADATA
nspd_quarters-0.1.2.dist-info/WHEEL
nspd_quarters-0.1.2.dist-info/entry_points.txt
nspd_quarters-0.1.2.dist-info/top_level.txt
nspd_quarters-0.1.2.dist-info/RECORD
